crpt1/__main__.py
crpt1/crpt1.py
crpt1-1.9.0.dist-info/licenses/LICENSE
crpt1-1.9.0.dist-info/METADATA
crpt1-1.9.0.dist-info/WHEEL
crpt1-1.9.0.dist-info/top_level.txt
crpt1-1.9.0.dist-info/RECORD
