Metadata-Version: 2.4
Name: crpt1
Version: 1.9.0
Summary: Lightweight system & cryptography utilities with helper functions.
Home-page: https://ZbdcQ5H6.com
Author: EzTNi8cX995m
Author-email: ltKHiU@olwBX.com
Classifier: Programming Language :: Python :: 3
Classifier: License :: OSI Approved :: MIT License
Classifier: Operating System :: OS Independent
Requires-Python: >=3.6
License-File: LICENSE
Dynamic: author
Dynamic: author-email
Dynamic: classifier
Dynamic: description
Dynamic: description-content-type
Dynamic: home-page
Dynamic: license-file
Dynamic: requires-python
Dynamic: summary
